attestable_mcp_server/__init__.py
attestable_mcp_server/__main__.py
attestable_mcp_server/server.py
gramine-ratls/__init__.py
gramine-ratls/attest.py
gramine-ratls/verify.py
mseep_attestable_mcp_server-0.1.4.dist-info/METADATA
mseep_attestable_mcp_server-0.1.4.dist-info/WHEEL
mseep_attestable_mcp_server-0.1.4.dist-info/entry_points.txt
mseep_attestable_mcp_server-0.1.4.dist-info/top_level.txt
mseep_attestable_mcp_server-0.1.4.dist-info/RECORD
