Metadata-Version: 2.4
Name: mseep-attestable-mcp-server
Version: 0.1.4
Summary: Add your description here
Author-email: mseep <support@skydeck.ai>
Requires-Python: >=3.13
Requires-Dist: anyio>=4.5
Requires-Dist: httpx>=0.27
Requires-Dist: httpx-sse>=0.4
Requires-Dist: pydantic<3.0.0,>=2.7.2
Requires-Dist: starlette>=0.27
Requires-Dist: sse-starlette>=1.6.1
Requires-Dist: pydantic-settings>=2.5.2
Requires-Dist: uvicorn>=0.23.1
Requires-Dist: docker>=7.1.0
Requires-Dist: jinja2>=3.1.6
Requires-Dist: tomli>=2.2.1
Requires-Dist: tomli-w>=1.2.0
Requires-Dist: pyyaml>=6.0.2
Requires-Dist: fastapi>=0.115.12
